{
  "_comment": "Tydro on Ink mainnet (chainId 57073). Only the addressesProvider, dataProvider and oracleMigrationTarget are read by scripts/tests; pool/configurator/oracle/aclManager/aclAdmin are DERIVED at runtime from the provider and listed here for reference only. All values verified on-chain at the pinned fork block.",
  "addressesProvider": "0x4172E6aAEC070ACB31aaCE343A58c93E4C70f44D",
  "dataProvider": "0x96086C25d13943C80Ff9a19791a40Df6aFC08328",
  "oracleMigrationTarget": "0x4200000000000000000000000000000000000006",
  "_derived_for_reference_only": {
    "pool": "0x2816cf15F6d2A220E789aA011D5EE4eB6c47FEbA",
    "poolConfigurator": "0x4f221e5c0B7103f7e3291E10097de6D9e3BfC02d",
    "priceOracle": "0x4758213271BFdC72224A7a8742dC865fC97756e1",
    "aclManager": "0x86E2938daE289763D4e09a7e42c5cCcA62Cf9809",
    "aclAdmin": "0x1dF462e2712496373A347f8ad10802a5E95f053D"
  },
  "_abi_hints": {
    "_comment": "Reference only — NOT read by scripts/tests. Human-readable signatures for ad-hoc `cast` against the running fork, e.g. `cast call $POOL 'getReservesList()(address[])'`. Full Solidity interfaces live in src/interfaces/IAaveV3.sol; this is intentionally a small cast cheat-sheet, not a duplicated ABI.",
    "pool": [
      "getReservesList()(address[])",
      "getUserAccountData(address)(uint256,uint256,uint256,uint256,uint256,uint256)",
      "supply(address,uint256,address,uint16)",
      "withdraw(address,uint256,address)(uint256)",
      "borrow(address,uint256,uint256,uint16,address)",
      "setUserUseReserveAsCollateral(address,bool)"
    ],
    "priceOracle": [
      "getAssetPrice(address)(uint256)",
      "getSourceOfAsset(address)(address)",
      "setAssetSources(address[],address[])",
      "BASE_CURRENCY_UNIT()(uint256)"
    ],
    "poolConfigurator": [
      "configureReserveAsCollateral(address,uint256,uint256,uint256)",
      "setReserveFactor(address,uint256)",
      "setSupplyCap(address,uint256)",
      "setBorrowCap(address,uint256)",
      "setReserveBorrowing(address,bool)"
    ],
    "aclManager": [
      "isPoolAdmin(address)(bool)",
      "addPoolAdmin(address)",
      "hasRole(bytes32,address)(bool)",
      "DEFAULT_ADMIN_ROLE()(bytes32)"
    ],
    "dataProvider": [
      "getReserveConfigurationData(address)(uint256,uint256,uint256,uint256,uint256,bool,bool,bool,bool,bool)",
      "getReserveTokensAddresses(address)(address,address,address)",
      "getReserveCaps(address)(uint256,uint256)"
    ]
  },
  "seed": {
    "_comment": "Position-book seeding (ForkBase.seedPositionBook). Read by scripts/tests; overridable per-key via SEED_* env vars; unset/zero fails loudly. Collateral is oracleMigrationTarget. borrowAsset defaults to USDC (deep, borrowing-enabled stable). lp/borrower1/borrower2 are anvil accounts #1/#2/#3 (public test keys) — deliberately NOT the candidate's account 0. HFs are basis points (10000 = 1.0): one comfortable, one near the edge.",
    "borrowAsset": "0x2D270e6886d130D724215A266106e6832161EAEd",
    "lp": "0x70997970C51812dc3A010C7d01b50e0d17dc79C8",
    "borrower1": "0x3C44CdDdB6a900fa2b585dd299e03d12FA4293BC",
    "borrower2": "0x90F79bf6EB2c4f870365E785982E1f101E93b906",
    "targetHfBps1": 20000,
    "targetHfBps2": 11500,
    "collateralWholeTokens": 10
  }
}
